reacttrs/__init__.py
reacttrs/py.typed
reacttrs/reactive.py
reacttrs-0.2.1.dist-info/METADATA
reacttrs-0.2.1.dist-info/WHEEL
reacttrs-0.2.1.dist-info/licenses/LICENSE
reacttrs-0.2.1.dist-info/RECORD
