Metadata-Version: 2.3
Name: reacttrs
Version: 0.2.1
Summary: Attributes with superpowers
Project-URL: Homepage, https://github.com/davidbrochart/reacttrs
Author-email: David Brochart <david.brochart@gmail.com>, Will McGugan <willmcgugan@gmail.com>
License-Expression: MIT
License-File: LICENSE
Requires-Python: >=3.8
Provides-Extra: test
Requires-Dist: mypy>=1.9.0; extra == 'test'
Requires-Dist: pytest>=8.1.1; extra == 'test'
